[
  {
    "id": 1,
    "pk": 1,
    "title": "신규 음료 메뉴 출시 안내",
    "author": "김사장",
    "date": "2024-04-28"
  },
  {
    "id": 2,
    "pk": 2,
    "title": "주말 영업 안내",
    "author": "이사장",
    "date": "2024-04-27"
  },
  {
    "id": 3,
    "pk": 3,
    "title": "커피 시음 이벤트 진행 중!",
    "author": "박사장",
    "date": "2024-04-25"
  },
  {
    "id": 4,
    "pk": 4,
    "title": "당일 주문은 1시간 이내에 수령 바랍니다.",
    "author": "김사장",
    "date": "2024-04-24"
  },
  {
    "id": 5,
    "pk": 5,
    "title": "휴업 안내",
    "author": "이사장",
    "date": "2024-04-20"
  },
  {
    "id": 6,
    "pk": 6,
    "title": "카페 내부 리모델링 공사 진행 중",
    "author": "박사장",
    "date": "2024-04-18"
  },
  {
    "id": 7,
    "pk": 7,
    "title": "환영합니다! 신규 고객 대상 할인 이벤트",
    "author": "김사장",
    "date": "2024-04-15"
  },
  {
    "id": 8,
    "pk": 8,
    "title": "오늘부터 더운 날씨에 맞춘 음료 출시!",
    "author": "이사장",
    "date": "2024-04-12"
  },
  {
    "id": 9,
    "pk": 9,
    "title": "휴무 일정 안내",
    "author": "박사장",
    "date": "2024-04-10"
  },
  {
    "id": 10,
    "pk": 10,
    "title": "고객 감사 이벤트 참여 안내",
    "author": "김사장",
    "date": "2024-04-08"
  }
]
